guitab/__init__.py
guitab/_version.py
guitab/guitab.py
guitab/tab.py
guitab/tests/__init__.py
guitab/tests/conftest.py
guitab/tests/global_test_data.py
guitab/tests/test_guitab.py
guitab/tests/test_tab.py
guitab-1.0.0.dist-info/AUTHORS.rst
guitab-1.0.0.dist-info/LICENSE
guitab-1.0.0.dist-info/METADATA
guitab-1.0.0.dist-info/WHEEL
guitab-1.0.0.dist-info/entry_points.txt
guitab-1.0.0.dist-info/top_level.txt
guitab-1.0.0.dist-info/RECORD
