Metadata-Version: 2.1
Name: guitab
Version: 1.0.0
Summary: Command-line interface for creating guitar tabs, implemented in Python
Home-page: https://github.com/bielsnohr/guitab
Author: bielsnohr
Author-email: matt.bielsnohr@protonmail.com
License: BSD (3-clause)
Platform: UNKNOWN
Classifier: Development Status :: 2 - Pre-Alpha
Classifier: Natural Language :: English
Classifier: Programming Language :: Python :: 3
Requires-Python: >=3.6
